{
    "name": "vd_flamethrower",
    "author": "Slepykat",
    "description": "Void Devourer Flamethrower",
    "emote":{
        "isLoop": "true",
        "returnTick": 15,
        "beginTick":8,
        "endTick":40,
        "stopTick":50,
        "degrees":false,
        "moves":[
            
            {
                "tick":8,
                "easing": "EASEINOUTQUAD",
                "turn": 0,
                "head":{
                    "y":-0.0
                }
            },
            {
                "tick":11,
                "easing": "EASEINOUTQUAD",
                "turn": 0,
                "head":{
                    "y":-0.0
                }
            },
            {
                "tick":8,
                "easing": "EASEINOUTQUAD",
                "turn": 0,
                "head":{
                    "z":-0.0
                }
            },
            {
                "tick":11,
                "easing": "EASEINOUTQUAD",
                "turn": 0,
                "head":{
                    "z":-0.0
                }
            },
            {
                "tick":8,
                "easing": "EASEINOUTQUAD",
                "turn": 0,
                "head":{
                    "x":-0.0
                }
            },
            {
                "tick":11,
                "easing": "EASEINOUTQUAD",
                "turn": 0,
                "head":{
                    "x":-0.0
                }
            },
            {
                "tick":8,
                "easing": "EASEINOUTQUAD",
                "turn": 0,
                "head":{
                    "yaw":-0.942873477935791
                }
            },
            {
                "tick":11,
                "easing": "EASEINOUTQUAD",
                "turn": 0,
                "head":{
                    "yaw":0.8787403106689453
                }
            },
            {
                "tick":8,
                "easing": "EASEINOUTQUAD",
                "turn": 0,
                "head":{
                    "roll":-0.17784331738948822
                }
            },
            {
                "tick":11,
                "easing": "EASEINOUTQUAD",
                "turn": 0,
                "head":{
                    "roll":0.17657707631587982
                }
            },
            {
                "tick":8,
                "easing": "EASEINOUTQUAD",
                "turn": 0,
                "head":{
                    "pitch":0.19349375367164612
                }
            },
            {
                "tick":11,
                "easing": "EASEINOUTQUAD",
                "turn": 0,
                "head":{
                    "pitch":-0.11011399328708649
                }
            },
            {
                "tick":8,
                "easing": "EASEINOUTQUAD",
                "turn": 0,
                "torso":{
                    "yaw":-0.924090564250946
                }
            },
            {
                "tick":9,
                "easing": "EASEINOUTQUAD",
                "turn": 0,
                "torso":{
                    "yaw":-0.5302478671073914
                }
            },
            {
                "tick":11,
                "easing": "EASEINOUTQUAD",
                "turn": 0,
                "torso":{
                    "yaw":0.8453484773635864
                }
            },
            {
                "tick":40,
                "easing": "EASEINOUTQUAD",
                "turn": 0,
                "torso":{
                    "yaw":0.8453484773635864
                }
            },
            {
                "tick":8,
                "easing": "EASEINOUTQUAD",
                "turn": 0,
                "torso":{
                    "roll":-0.16463720798492432
                }
            },
            {
                "tick":9,
                "easing": "EASEINOUTQUAD",
                "turn": 0,
                "torso":{
                    "roll":-0.03947354853153229
                }
            },
            {
                "tick":11,
                "easing": "EASEINOUTQUAD",
                "turn": 0,
                "torso":{
                    "roll":-0.4231925308704376
                }
            },
            {
                "tick":40,
                "easing": "EASEINOUTQUAD",
                "turn": 0,
                "torso":{
                    "roll":-0.4231925308704376
                }
            },
            {
                "tick":8,
                "easing": "EASEINOUTQUAD",
                "turn": 0,
                "torso":{
                    "pitch":0.20822015404701233
                }
            },
            {
                "tick":9,
                "easing": "EASEINOUTQUAD",
                "turn": 0,
                "torso":{
                    "pitch":-0.04381925240159035
                }
            },
            {
                "tick":11,
                "easing": "EASEINOUTQUAD",
                "turn": 0,
                "torso":{
                    "pitch":-0.39199572801589966
                }
            },
            {
                "tick":40,
                "easing": "EASEINOUTQUAD",
                "turn": 0,
                "torso":{
                    "pitch":-0.39199572801589966
                }
            },
            {
                "tick":8,
                "easing": "EASEINOUTQUAD",
                "turn": 0,
                "torso":{
                    "y":0.022970279678702354
                }
            },
            {
                "tick":9,
                "easing": "EASEINOUTQUAD",
                "turn": 0,
                "torso":{
                    "y":-0.007656756788492203
                }
            },
            {
                "tick":11,
                "easing": "EASEINOUTQUAD",
                "turn": 0,
                "torso":{
                    "y":0.030891919508576393
                }
            },
            {
                "tick":40,
                "easing": "EASEINOUTQUAD",
                "turn": 0,
                "torso":{
                    "y":0.0038283783942461014
                }
            },
            {
                "tick":8,
                "easing": "EASEINOUTQUAD",
                "turn": 0,
                "torso":{
                    "x":0.0
                }
            },
            {
                "tick":9,
                "easing": "EASEINOUTQUAD",
                "turn": 0,
                "torso":{
                    "x":0.0
                }
            },
            {
                "tick":11,
                "easing": "EASEINOUTQUAD",
                "turn": 0,
                "torso":{
                    "x":0.0
                }
            },
            {
                "tick":40,
                "easing": "EASEINOUTQUAD",
                "turn": 0,
                "torso":{
                    "x":0.0
                }
            },
            {
                "tick":8,
                "easing": "EASEINOUTQUAD",
                "turn": 0,
                "torso":{
                    "z":0.045940548181533813
                }
            },
            {
                "tick":9,
                "easing": "EASEINOUTQUAD",
                "turn": 0,
                "torso":{
                    "z":-0.0
                }
            },
            {
                "tick":11,
                "easing": "EASEINOUTQUAD",
                "turn": 0,
                "torso":{
                    "z":-0.2411879003047943
                }
            },
            {
                "tick":40,
                "easing": "EASEINOUTQUAD",
                "turn": 0,
                "torso":{
                    "z":-0.2411879003047943
                }
            },
            {
                "tick":8,
                "easing": "EASEINOUTQUAD",
                "turn": 0,
                "rightArm":{
                    "yaw":-0.9352416396141052
                }
            },
            {
                "tick":11,
                "easing": "EASEINOUTQUAD",
                "turn": 0,
                "rightArm":{
                    "yaw":0.8494243621826172
                }
            },
            {
                "tick":12,
                "easing": "EASEINOUTQUAD",
                "turn": 0,
                "rightArm":{
                    "yaw":0.8433804512023926
                }
            },
            {
                "tick":13,
                "easing": "EASEINOUTQUAD",
                "turn": 0,
                "rightArm":{
                    "yaw":0.8513936400413513
                }
            },
            {
                "tick":14,
                "easing": "EASEINOUTQUAD",
                "turn": 0,
                "rightArm":{
                    "yaw":0.8494243621826172
                }
            },
            {
                "tick":15,
                "easing": "EASEINOUTQUAD",
                "turn": 0,
                "rightArm":{
                    "yaw":0.8433804512023926
                }
            },
            {
                "tick":16,
                "easing": "EASEINOUTQUAD",
                "turn": 0,
                "rightArm":{
                    "yaw":0.8513936400413513
                }
            },
            {
                "tick":17,
                "easing": "EASEINOUTQUAD",
                "turn": 0,
                "rightArm":{
                    "yaw":0.8494243621826172
                }
            },
            {
                "tick":18,
                "easing": "EASEINOUTQUAD",
                "turn": 0,
                "rightArm":{
                    "yaw":0.8433804512023926
                }
            },
            {
                "tick":19,
                "easing": "EASEINOUTQUAD",
                "turn": 0,
                "rightArm":{
                    "yaw":0.8513936400413513
                }
            },
            {
                "tick":20,
                "easing": "EASEINOUTQUAD",
                "turn": 0,
                "rightArm":{
                    "yaw":0.8494243621826172
                }
            },
            {
                "tick":21,
                "easing": "EASEINOUTQUAD",
                "turn": 0,
                "rightArm":{
                    "yaw":0.8433804512023926
                }
            },
            {
                "tick":22,
                "easing": "EASEINOUTQUAD",
                "turn": 0,
                "rightArm":{
                    "yaw":0.8513936400413513
                }
            },
            {
                "tick":23,
                "easing": "EASEINOUTQUAD",
                "turn": 0,
                "rightArm":{
                    "yaw":0.8494243621826172
                }
            },
            {
                "tick":24,
                "easing": "EASEINOUTQUAD",
                "turn": 0,
                "rightArm":{
                    "yaw":0.8433804512023926
                }
            },
            {
                "tick":25,
                "easing": "EASEINOUTQUAD",
                "turn": 0,
                "rightArm":{
                    "yaw":0.8513936400413513
                }
            },
            {
                "tick":26,
                "easing": "EASEINOUTQUAD",
                "turn": 0,
                "rightArm":{
                    "yaw":0.8494243621826172
                }
            },
            {
                "tick":27,
                "easing": "EASEINOUTQUAD",
                "turn": 0,
                "rightArm":{
                    "yaw":0.8433804512023926
                }
            },
            {
                "tick":28,
                "easing": "EASEINOUTQUAD",
                "turn": 0,
                "rightArm":{
                    "yaw":0.8513936400413513
                }
            },
            {
                "tick":29,
                "easing": "EASEINOUTQUAD",
                "turn": 0,
                "rightArm":{
                    "yaw":0.8494243621826172
                }
            },
            {
                "tick":30,
                "easing": "EASEINOUTQUAD",
                "turn": 0,
                "rightArm":{
                    "yaw":0.8433804512023926
                }
            },
            {
                "tick":31,
                "easing": "EASEINOUTQUAD",
                "turn": 0,
                "rightArm":{
                    "yaw":0.8513936400413513
                }
            },
            {
                "tick":32,
                "easing": "EASEINOUTQUAD",
                "turn": 0,
                "rightArm":{
                    "yaw":0.8494243621826172
                }
            },
            {
                "tick":33,
                "easing": "EASEINOUTQUAD",
                "turn": 0,
                "rightArm":{
                    "yaw":0.8433804512023926
                }
            },
            {
                "tick":34,
                "easing": "EASEINOUTQUAD",
                "turn": 0,
                "rightArm":{
                    "yaw":0.8513936400413513
                }
            },
            {
                "tick":40,
                "easing": "EASEINOUTQUAD",
                "turn": 0,
                "rightArm":{
                    "yaw":0.8183543682098389
                }
            },
            {
                "tick":8,
                "easing": "EASEINOUTQUAD",
                "turn": 0,
                "rightArm":{
                    "roll":-0.02175898849964142
                }
            },
            {
                "tick":11,
                "easing": "EASEINOUTQUAD",
                "turn": 0,
                "rightArm":{
                    "roll":0.18247170746326447
                }
            },
            {
                "tick":12,
                "easing": "EASEINOUTQUAD",
                "turn": 0,
                "rightArm":{
                    "roll":0.232112854719162
                }
            },
            {
                "tick":13,
                "easing": "EASEINOUTQUAD",
                "turn": 0,
                "rightArm":{
                    "roll":0.14146430790424347
                }
            },
            {
                "tick":14,
                "easing": "EASEINOUTQUAD",
                "turn": 0,
                "rightArm":{
                    "roll":0.18247170746326447
                }
            },
            {
                "tick":15,
                "easing": "EASEINOUTQUAD",
                "turn": 0,
                "rightArm":{
                    "roll":0.232112854719162
                }
            },
            {
                "tick":16,
                "easing": "EASEINOUTQUAD",
                "turn": 0,
                "rightArm":{
                    "roll":0.14146430790424347
                }
            },
            {
                "tick":17,
                "easing": "EASEINOUTQUAD",
                "turn": 0,
                "rightArm":{
                    "roll":0.18247170746326447
                }
            },
            {
                "tick":18,
                "easing": "EASEINOUTQUAD",
                "turn": 0,
                "rightArm":{
                    "roll":0.232112854719162
                }
            },
            {
                "tick":19,
                "easing": "EASEINOUTQUAD",
                "turn": 0,
                "rightArm":{
                    "roll":0.14146430790424347
                }
            },
            {
                "tick":20,
                "easing": "EASEINOUTQUAD",
                "turn": 0,
                "rightArm":{
                    "roll":0.18247170746326447
                }
            },
            {
                "tick":21,
                "easing": "EASEINOUTQUAD",
                "turn": 0,
                "rightArm":{
                    "roll":0.232112854719162
                }
            },
            {
                "tick":22,
                "easing": "EASEINOUTQUAD",
                "turn": 0,
                "rightArm":{
                    "roll":0.14146430790424347
                }
            },
            {
                "tick":23,
                "easing": "EASEINOUTQUAD",
                "turn": 0,
                "rightArm":{
                    "roll":0.18247170746326447
                }
            },
            {
                "tick":24,
                "easing": "EASEINOUTQUAD",
                "turn": 0,
                "rightArm":{
                    "roll":0.232112854719162
                }
            },
            {
                "tick":25,
                "easing": "EASEINOUTQUAD",
                "turn": 0,
                "rightArm":{
                    "roll":0.14146430790424347
                }
            },
            {
                "tick":26,
                "easing": "EASEINOUTQUAD",
                "turn": 0,
                "rightArm":{
                    "roll":0.18247170746326447
                }
            },
            {
                "tick":27,
                "easing": "EASEINOUTQUAD",
                "turn": 0,
                "rightArm":{
                    "roll":0.232112854719162
                }
            },
            {
                "tick":28,
                "easing": "EASEINOUTQUAD",
                "turn": 0,
                "rightArm":{
                    "roll":0.14146430790424347
                }
            },
            {
                "tick":29,
                "easing": "EASEINOUTQUAD",
                "turn": 0,
                "rightArm":{
                    "roll":0.18247170746326447
                }
            },
            {
                "tick":30,
                "easing": "EASEINOUTQUAD",
                "turn": 0,
                "rightArm":{
                    "roll":0.232112854719162
                }
            },
            {
                "tick":31,
                "easing": "EASEINOUTQUAD",
                "turn": 0,
                "rightArm":{
                    "roll":0.14146430790424347
                }
            },
            {
                "tick":32,
                "easing": "EASEINOUTQUAD",
                "turn": 0,
                "rightArm":{
                    "roll":0.18247170746326447
                }
            },
            {
                "tick":33,
                "easing": "EASEINOUTQUAD",
                "turn": 0,
                "rightArm":{
                    "roll":0.232112854719162
                }
            },
            {
                "tick":34,
                "easing": "EASEINOUTQUAD",
                "turn": 0,
                "rightArm":{
                    "roll":0.14146430790424347
                }
            },
            {
                "tick":40,
                "easing": "EASEINOUTQUAD",
                "turn": 0,
                "rightArm":{
                    "roll":0.16976436972618103
                }
            },
            {
                "tick":8,
                "easing": "EASEINOUTQUAD",
                "turn": 0,
                "rightArm":{
                    "y":1.7903308868408203
                }
            },
            {
                "tick":11,
                "easing": "EASEINOUTQUAD",
                "turn": 0,
                "rightArm":{
                    "y":1.5768146514892578
                }
            },
            {
                "tick":14,
                "easing": "EASEINOUTQUAD",
                "turn": 0,
                "rightArm":{
                    "y":1.5768146514892578
                }
            },
            {
                "tick":17,
                "easing": "EASEINOUTQUAD",
                "turn": 0,
                "rightArm":{
                    "y":1.5768146514892578
                }
            },
            {
                "tick":20,
                "easing": "EASEINOUTQUAD",
                "turn": 0,
                "rightArm":{
                    "y":1.5768146514892578
                }
            },
            {
                "tick":23,
                "easing": "EASEINOUTQUAD",
                "turn": 0,
                "rightArm":{
                    "y":1.5768146514892578
                }
            },
            {
                "tick":26,
                "easing": "EASEINOUTQUAD",
                "turn": 0,
                "rightArm":{
                    "y":1.5768146514892578
                }
            },
            {
                "tick":29,
                "easing": "EASEINOUTQUAD",
                "turn": 0,
                "rightArm":{
                    "y":1.5768146514892578
                }
            },
            {
                "tick":32,
                "easing": "EASEINOUTQUAD",
                "turn": 0,
                "rightArm":{
                    "y":1.5768146514892578
                }
            },
            {
                "tick":40,
                "easing": "EASEINOUTQUAD",
                "turn": 0,
                "rightArm":{
                    "y":1.944772720336914
                }
            },
            {
                "tick":8,
                "easing": "EASEINOUTQUAD",
                "turn": 0,
                "rightArm":{
                    "z":-0.5115378499031067
                }
            },
            {
                "tick":11,
                "easing": "EASEINOUTQUAD",
                "turn": 0,
                "rightArm":{
                    "z":-2.682337760925293
                }
            },
            {
                "tick":14,
                "easing": "EASEINOUTQUAD",
                "turn": 0,
                "rightArm":{
                    "z":-2.682337760925293
                }
            },
            {
                "tick":17,
                "easing": "EASEINOUTQUAD",
                "turn": 0,
                "rightArm":{
                    "z":-2.682337760925293
                }
            },
            {
                "tick":20,
                "easing": "EASEINOUTQUAD",
                "turn": 0,
                "rightArm":{
                    "z":-2.682337760925293
                }
            },
            {
                "tick":23,
                "easing": "EASEINOUTQUAD",
                "turn": 0,
                "rightArm":{
                    "z":-2.682337760925293
                }
            },
            {
                "tick":26,
                "easing": "EASEINOUTQUAD",
                "turn": 0,
                "rightArm":{
                    "z":-2.682337760925293
                }
            },
            {
                "tick":29,
                "easing": "EASEINOUTQUAD",
                "turn": 0,
                "rightArm":{
                    "z":-2.682337760925293
                }
            },
            {
                "tick":32,
                "easing": "EASEINOUTQUAD",
                "turn": 0,
                "rightArm":{
                    "z":-2.682337760925293
                }
            },
            {
                "tick":40,
                "easing": "EASEINOUTQUAD",
                "turn": 0,
                "rightArm":{
                    "z":-2.1115078926086426
                }
            },
            {
                "tick":8,
                "easing": "EASEINOUTQUAD",
                "turn": 0,
                "rightArm":{
                    "x":-7.499961853027344
                }
            },
            {
                "tick":11,
                "easing": "EASEINOUTQUAD",
                "turn": 0,
                "rightArm":{
                    "x":-5.566961288452148
                }
            },
            {
                "tick":14,
                "easing": "EASEINOUTQUAD",
                "turn": 0,
                "rightArm":{
                    "x":-5.566961288452148
                }
            },
            {
                "tick":17,
                "easing": "EASEINOUTQUAD",
                "turn": 0,
                "rightArm":{
                    "x":-5.566961288452148
                }
            },
            {
                "tick":20,
                "easing": "EASEINOUTQUAD",
                "turn": 0,
                "rightArm":{
                    "x":-5.566961288452148
                }
            },
            {
                "tick":23,
                "easing": "EASEINOUTQUAD",
                "turn": 0,
                "rightArm":{
                    "x":-5.566961288452148
                }
            },
            {
                "tick":26,
                "easing": "EASEINOUTQUAD",
                "turn": 0,
                "rightArm":{
                    "x":-5.566961288452148
                }
            },
            {
                "tick":29,
                "easing": "EASEINOUTQUAD",
                "turn": 0,
                "rightArm":{
                    "x":-5.566961288452148
                }
            },
            {
                "tick":32,
                "easing": "EASEINOUTQUAD",
                "turn": 0,
                "rightArm":{
                    "x":-5.566961288452148
                }
            },
            {
                "tick":40,
                "easing": "EASEINOUTQUAD",
                "turn": 0,
                "rightArm":{
                    "x":-4.896336078643799
                }
            },
            {
                "tick":8,
                "easing": "EASEINOUTQUAD",
                "turn": 0,
                "rightArm":{
                    "pitch":-1.3580362796783447
                }
            },
            {
                "tick":11,
                "easing": "EASEINOUTQUAD",
                "turn": 0,
                "rightArm":{
                    "pitch":-1.6840590238571167
                }
            },
            {
                "tick":12,
                "easing": "EASEINOUTQUAD",
                "turn": 0,
                "rightArm":{
                    "pitch":-1.6818718910217285
                }
            },
            {
                "tick":13,
                "easing": "EASEINOUTQUAD",
                "turn": 0,
                "rightArm":{
                    "pitch":-1.694715142250061
                }
            },
            {
                "tick":14,
                "easing": "EASEINOUTQUAD",
                "turn": 0,
                "rightArm":{
                    "pitch":-1.6840590238571167
                }
            },
            {
                "tick":15,
                "easing": "EASEINOUTQUAD",
                "turn": 0,
                "rightArm":{
                    "pitch":-1.6818718910217285
                }
            },
            {
                "tick":16,
                "easing": "EASEINOUTQUAD",
                "turn": 0,
                "rightArm":{
                    "pitch":-1.694715142250061
                }
            },
            {
                "tick":17,
                "easing": "EASEINOUTQUAD",
                "turn": 0,
                "rightArm":{
                    "pitch":-1.6840590238571167
                }
            },
            {
                "tick":18,
                "easing": "EASEINOUTQUAD",
                "turn": 0,
                "rightArm":{
                    "pitch":-1.6818718910217285
                }
            },
            {
                "tick":19,
                "easing": "EASEINOUTQUAD",
                "turn": 0,
                "rightArm":{
                    "pitch":-1.694715142250061
                }
            },
            {
                "tick":20,
                "easing": "EASEINOUTQUAD",
                "turn": 0,
                "rightArm":{
                    "pitch":-1.6840590238571167
                }
            },
            {
                "tick":21,
                "easing": "EASEINOUTQUAD",
                "turn": 0,
                "rightArm":{
                    "pitch":-1.6818718910217285
                }
            },
            {
                "tick":22,
                "easing": "EASEINOUTQUAD",
                "turn": 0,
                "rightArm":{
                    "pitch":-1.694715142250061
                }
            },
            {
                "tick":23,
                "easing": "EASEINOUTQUAD",
                "turn": 0,
                "rightArm":{
                    "pitch":-1.6840590238571167
                }
            },
            {
                "tick":24,
                "easing": "EASEINOUTQUAD",
                "turn": 0,
                "rightArm":{
                    "pitch":-1.6818718910217285
                }
            },
            {
                "tick":25,
                "easing": "EASEINOUTQUAD",
                "turn": 0,
                "rightArm":{
                    "pitch":-1.694715142250061
                }
            },
            {
                "tick":26,
                "easing": "EASEINOUTQUAD",
                "turn": 0,
                "rightArm":{
                    "pitch":-1.6840590238571167
                }
            },
            {
                "tick":27,
                "easing": "EASEINOUTQUAD",
                "turn": 0,
                "rightArm":{
                    "pitch":-1.6818718910217285
                }
            },
            {
                "tick":28,
                "easing": "EASEINOUTQUAD",
                "turn": 0,
                "rightArm":{
                    "pitch":-1.694715142250061
                }
            },
            {
                "tick":29,
                "easing": "EASEINOUTQUAD",
                "turn": 0,
                "rightArm":{
                    "pitch":-1.6840590238571167
                }
            },
            {
                "tick":30,
                "easing": "EASEINOUTQUAD",
                "turn": 0,
                "rightArm":{
                    "pitch":-1.6818718910217285
                }
            },
            {
                "tick":31,
                "easing": "EASEINOUTQUAD",
                "turn": 0,
                "rightArm":{
                    "pitch":-1.694715142250061
                }
            },
            {
                "tick":32,
                "easing": "EASEINOUTQUAD",
                "turn": 0,
                "rightArm":{
                    "pitch":-1.6840590238571167
                }
            },
            {
                "tick":33,
                "easing": "EASEINOUTQUAD",
                "turn": 0,
                "rightArm":{
                    "pitch":-1.6818718910217285
                }
            },
            {
                "tick":34,
                "easing": "EASEINOUTQUAD",
                "turn": 0,
                "rightArm":{
                    "pitch":-1.694715142250061
                }
            },
            {
                "tick":40,
                "easing": "EASEINOUTQUAD",
                "turn": 0,
                "rightArm":{
                    "pitch":-1.7301989793777466
                }
            },
            {
                "tick":8,
                "easing": "EASEINOUTQUAD",
                "turn": 0,
                "leftArm":{
                    "roll":-0.5461918711662292
                }
            },
            {
                "tick":11,
                "easing": "EASEINOUTQUAD",
                "turn": 0,
                "leftArm":{
                    "roll":0.9193534255027771
                }
            },
            {
                "tick":35,
                "easing": "EASEINOUTQUAD",
                "turn": 0,
                "leftArm":{
                    "roll":0.9193534255027771
                }
            },
            {
                "tick":40,
                "easing": "EASEINOUTQUAD",
                "turn": 0,
                "leftArm":{
                    "roll":1.078482985496521
                }
            },
            {
                "tick":8,
                "easing": "EASEINOUTQUAD",
                "turn": 0,
                "leftArm":{
                    "yaw":-0.43693816661834717
                }
            },
            {
                "tick":11,
                "easing": "EASEINOUTQUAD",
                "turn": 0,
                "leftArm":{
                    "yaw":0.8752523064613342
                }
            },
            {
                "tick":35,
                "easing": "EASEINOUTQUAD",
                "turn": 0,
                "leftArm":{
                    "yaw":0.8752523064613342
                }
            },
            {
                "tick":40,
                "easing": "EASEINOUTQUAD",
                "turn": 0,
                "leftArm":{
                    "yaw":0.32779622077941895
                }
            },
            {
                "tick":8,
                "easing": "EASEINOUTQUAD",
                "turn": 0,
                "leftArm":{
                    "pitch":-0.09042450785636902
                }
            },
            {
                "tick":11,
                "easing": "EASEINOUTQUAD",
                "turn": 0,
                "leftArm":{
                    "pitch":-1.0276150703430176
                }
            },
            {
                "tick":35,
                "easing": "EASEINOUTQUAD",
                "turn": 0,
                "leftArm":{
                    "pitch":-1.0276150703430176
                }
            },
            {
                "tick":40,
                "easing": "EASEINOUTQUAD",
                "turn": 0,
                "leftArm":{
                    "pitch":-0.5240082144737244
                }
            },
            {
                "tick":8,
                "easing": "EASEINOUTQUAD",
                "turn": 0,
                "leftArm":{
                    "y":2.438352584838867
                }
            },
            {
                "tick":11,
                "easing": "EASEINOUTQUAD",
                "turn": 0,
                "leftArm":{
                    "y":2.710476875305176
                }
            },
            {
                "tick":35,
                "easing": "EASEINOUTQUAD",
                "turn": 0,
                "leftArm":{
                    "y":2.710476875305176
                }
            },
            {
                "tick":40,
                "easing": "EASEINOUTQUAD",
                "turn": 0,
                "leftArm":{
                    "y":3.411050796508789
                }
            },
            {
                "tick":8,
                "easing": "EASEINOUTQUAD",
                "turn": 0,
                "leftArm":{
                    "z":1.653830885887146
                }
            },
            {
                "tick":11,
                "easing": "EASEINOUTQUAD",
                "turn": 0,
                "leftArm":{
                    "z":-1.5142278671264648
                }
            },
            {
                "tick":35,
                "easing": "EASEINOUTQUAD",
                "turn": 0,
                "leftArm":{
                    "z":-1.5142278671264648
                }
            },
            {
                "tick":40,
                "easing": "EASEINOUTQUAD",
                "turn": 0,
                "leftArm":{
                    "z":-1.1469979286193848
                }
            },
            {
                "tick":8,
                "easing": "EASEINOUTQUAD",
                "turn": 0,
                "leftArm":{
                    "x":3.856553554534912
                }
            },
            {
                "tick":11,
                "easing": "EASEINOUTQUAD",
                "turn": 0,
                "leftArm":{
                    "x":2.0604195594787598
                }
            },
            {
                "tick":35,
                "easing": "EASEINOUTQUAD",
                "turn": 0,
                "leftArm":{
                    "x":2.0604195594787598
                }
            },
            {
                "tick":40,
                "easing": "EASEINOUTQUAD",
                "turn": 0,
                "leftArm":{
                    "x":2.422977924346924
                }
            },
            {
                "tick":8,
                "easing": "EASEINOUTQUAD",
                "turn": 0,
                "rightLeg":{
                    "yaw":-0.9342395067214966
                }
            },
            {
                "tick":11,
                "easing": "EASEINOUTQUAD",
                "turn": 0,
                "rightLeg":{
                    "yaw":1.0214630365371704
                }
            },
            {
                "tick":40,
                "easing": "EASEINOUTQUAD",
                "turn": 0,
                "rightLeg":{
                    "yaw":1.0216636657714844
                }
            },
            {
                "tick":8,
                "easing": "EASEINOUTQUAD",
                "turn": 0,
                "rightLeg":{
                    "roll":-0.021146517246961594
                }
            },
            {
                "tick":11,
                "easing": "EASEINOUTQUAD",
                "turn": 0,
                "rightLeg":{
                    "roll":0.16899487376213074
                }
            },
            {
                "tick":40,
                "easing": "EASEINOUTQUAD",
                "turn": 0,
                "rightLeg":{
                    "roll":0.17202934622764587
                }
            },
            {
                "tick":8,
                "easing": "EASEINOUTQUAD",
                "turn": 0,
                "rightLeg":{
                    "pitch":0.26511508226394653
                }
            },
            {
                "tick":11,
                "easing": "EASEINOUTQUAD",
                "turn": 0,
                "rightLeg":{
                    "pitch":-0.17089061439037323
                }
            },
            {
                "tick":40,
                "easing": "EASEINOUTQUAD",
                "turn": 0,
                "rightLeg":{
                    "pitch":-0.15458162128925323
                }
            },
            {
                "tick":8,
                "easing": "EASEINOUTQUAD",
                "turn": 0,
                "rightLeg":{
                    "x":-1.9
                }
            },
            {
                "tick":11,
                "easing": "EASEINOUTQUAD",
                "turn": 0,
                "rightLeg":{
                    "x":-2.1220280170440673
                }
            },
            {
                "tick":40,
                "easing": "EASEINOUTQUAD",
                "turn": 0,
                "rightLeg":{
                    "x":-2.1389616966247558
                }
            },
            {
                "tick":8,
                "easing": "EASEINOUTQUAD",
                "turn": 0,
                "rightLeg":{
                    "y":12.0
                }
            },
            {
                "tick":11,
                "easing": "EASEINOUTQUAD",
                "turn": 0,
                "rightLeg":{
                    "y":11.924783647060394
                }
            },
            {
                "tick":40,
                "easing": "EASEINOUTQUAD",
                "turn": 0,
                "rightLeg":{
                    "y":11.573535799980164
                }
            },
            {
                "tick":8,
                "easing": "EASEINOUTQUAD",
                "turn": 0,
                "rightLeg":{
                    "z":0.1
                }
            },
            {
                "tick":11,
                "easing": "EASEINOUTQUAD",
                "turn": 0,
                "rightLeg":{
                    "z":-0.08195009231567382
                }
            },
            {
                "tick":40,
                "easing": "EASEINOUTQUAD",
                "turn": 0,
                "rightLeg":{
                    "z":-0.1480044960975647
                }
            },
            {
                "tick":8,
                "easing": "EASEINOUTQUAD",
                "turn": 0,
                "leftLeg":{
                    "yaw":-0.9793761968612671
                }
            },
            {
                "tick":11,
                "easing": "EASEINOUTQUAD",
                "turn": 0,
                "leftLeg":{
                    "yaw":0.9061048030853271
                }
            },
            {
                "tick":40,
                "easing": "EASEINOUTQUAD",
                "turn": 0,
                "leftLeg":{
                    "yaw":0.9064838886260986
                }
            },
            {
                "tick":8,
                "easing": "EASEINOUTQUAD",
                "turn": 0,
                "leftLeg":{
                    "roll":0.01612338237464428
                }
            },
            {
                "tick":11,
                "easing": "EASEINOUTQUAD",
                "turn": 0,
                "leftLeg":{
                    "roll":0.19713851809501648
                }
            },
            {
                "tick":40,
                "easing": "EASEINOUTQUAD",
                "turn": 0,
                "leftLeg":{
                    "roll":0.19720156490802765
                }
            },
            {
                "tick":8,
                "easing": "EASEINOUTQUAD",
                "turn": 0,
                "leftLeg":{
                    "pitch":-0.14034168422222137
                }
            },
            {
                "tick":11,
                "easing": "EASEINOUTQUAD",
                "turn": 0,
                "leftLeg":{
                    "pitch":0.34988150000572205
                }
            },
            {
                "tick":40,
                "easing": "EASEINOUTQUAD",
                "turn": 0,
                "leftLeg":{
                    "pitch":0.15184476971626282
                }
            },
            {
                "tick":8,
                "easing": "EASEINOUTQUAD",
                "turn": 0,
                "leftLeg":{
                    "y":10.897092938423157
                }
            },
            {
                "tick":11,
                "easing": "EASEINOUTQUAD",
                "turn": 0,
                "leftLeg":{
                    "y":12.424321860074997
                }
            },
            {
                "tick":40,
                "easing": "EASEINOUTQUAD",
                "turn": 0,
                "leftLeg":{
                    "y":12.318893671035767
                }
            },
            {
                "tick":8,
                "easing": "EASEINOUTQUAD",
                "turn": 0,
                "leftLeg":{
                    "z":-0.9573434948921203
                }
            },
            {
                "tick":11,
                "easing": "EASEINOUTQUAD",
                "turn": 0,
                "leftLeg":{
                    "z":0.5584224700927735
                }
            },
            {
                "tick":40,
                "easing": "EASEINOUTQUAD",
                "turn": 0,
                "leftLeg":{
                    "z":0.3033891558647156
                }
            },
            {
                "tick":8,
                "easing": "EASEINOUTQUAD",
                "turn": 0,
                "leftLeg":{
                    "x":3.068747901916504
                }
            },
            {
                "tick":11,
                "easing": "EASEINOUTQUAD",
                "turn": 0,
                "leftLeg":{
                    "x":2.673550033569336
                }
            },
            {
                "tick":40,
                "easing": "EASEINOUTQUAD",
                "turn": 0,
                "leftLeg":{
                    "x":2.3623408317565917
                }
            },
            {
                "tick":8,
                "easing": "EASEINOUTQUAD",
                "turn": 0,
                "rightItem":{
                    "x":1.48265540599823
                }
            },
            {
                "tick":11,
                "easing": "EASEINOUTQUAD",
                "turn": 0,
                "rightItem":{
                    "x":0.9817293882369995
                }
            },
            {
                "tick":40,
                "easing": "EASEINOUTQUAD",
                "turn": 0,
                "rightItem":{
                    "x":0.7624462246894836
                }
            },
            {
                "tick":8,
                "easing": "EASEINOUTQUAD",
                "turn": 0,
                "rightItem":{
                    "z":-0.5550249814987183
                }
            },
            {
                "tick":11,
                "easing": "EASEINOUTQUAD",
                "turn": 0,
                "rightItem":{
                    "z":-1.7770073413848877
                }
            },
            {
                "tick":40,
                "easing": "EASEINOUTQUAD",
                "turn": 0,
                "rightItem":{
                    "z":-0.4235007166862488
                }
            },
            {
                "tick":8,
                "easing": "EASEINOUTQUAD",
                "turn": 0,
                "rightItem":{
                    "y":-1.9703696966171265
                }
            },
            {
                "tick":11,
                "easing": "EASEINOUTQUAD",
                "turn": 0,
                "rightItem":{
                    "y":-2.079120397567749
                }
            },
            {
                "tick":40,
                "easing": "EASEINOUTQUAD",
                "turn": 0,
                "rightItem":{
                    "y":-2.4135324954986572
                }
            },
            {
                "tick":8,
                "easing": "EASEINOUTQUAD",
                "turn": 0,
                "rightItem":{
                    "pitch":-1.4232094287872314
                }
            },
            {
                "tick":11,
                "easing": "EASEINOUTQUAD",
                "turn": 0,
                "rightItem":{
                    "pitch":-1.37575364112854
                }
            },
            {
                "tick":40,
                "easing": "EASEINOUTQUAD",
                "turn": 0,
                "rightItem":{
                    "pitch":-1.3877264261245728
                }
            },
            {
                "tick":8,
                "easing": "EASEINOUTQUAD",
                "turn": 0,
                "rightItem":{
                    "yaw":-0.07281815260648727
                }
            },
            {
                "tick":11,
                "easing": "EASEINOUTQUAD",
                "turn": 0,
                "rightItem":{
                    "yaw":-0.001606406643986702
                }
            },
            {
                "tick":40,
                "easing": "EASEINOUTQUAD",
                "turn": 0,
                "rightItem":{
                    "yaw":-0.029175907373428345
                }
            },
            {
                "tick":8,
                "easing": "EASEINOUTQUAD",
                "turn": 0,
                "rightItem":{
                    "roll":1.5803109407424927
                }
            },
            {
                "tick":11,
                "easing": "EASEINOUTQUAD",
                "turn": 0,
                "rightItem":{
                    "roll":1.556544303894043
                }
            },
            {
                "tick":40,
                "easing": "EASEINOUTQUAD",
                "turn": 0,
                "rightItem":{
                    "roll":1.5412847995758057
                }
            }
        ]
    }
}